appion/__init__.py
appion/appion_logo.png
appion/bibtex.py
appion/constants.py
appion/protocols.conf
appion/wizards.py
appion/convert/__init__.py
appion/convert/convert.py
appion/convert/dataimport.py
appion/protocols/__init__.py
appion/protocols/protocol_dogpicker.py
scipion_em_appion-3.0.3.dist-info/LICENSE
scipion_em_appion-3.0.3.dist-info/METADATA
scipion_em_appion-3.0.3.dist-info/WHEEL
scipion_em_appion-3.0.3.dist-info/entry_points.txt
scipion_em_appion-3.0.3.dist-info/top_level.txt
scipion_em_appion-3.0.3.dist-info/RECORD
