Metadata-Version: 2.1
Name: scipion-em-appion
Version: 3.0.3
Summary: Plugin to use Appion Dogpicker within the Scipion framework
Home-page: https://github.com/scipion-em/scipion-em-appion
Author: I2PC
Author-email: scipion@cnb.csic.es
License: UNKNOWN
Keywords: scipion cryoem imageprocessing scipion-3.0
Platform: UNKNOWN
Requires-Dist: scipion-em
